tragic_semester_work_2/__init__.py
tragic_semester_work_2/constants.py
tragic_semester_work_2/counts_sort.py
tragic_semester_work_2/Generator.py
tragic_semester_work_2/load_testing_data/1_1.txt
tragic_semester_work_2/load_testing_data/2_1.txt
tragic_semester_work_2/load_testing_data/3_1.txt
tragic_semester_work_2/load_testing_data/4_1.txt
tragic_semester_work_2/load_testing_data/5_1.txt
tragic_semester_work_2/load_testing_data/6_1.txt
tragic_semester_work_2/load_testing_data/7_1.txt
tragic_semester_work_2/load_testing_data/8_1.txt
tragic_semester_work_2/load_testing_data/9_1.txt
tragic_semester_work_2/load_testing_measurements/1621627280.csv
tragic_semester_work_2/load_testing_measurements/1621659210.csv
tragic_semester_work_2/load_testing_measurements/1621664588.csv
tragic_semester_work_2/load_testing_measurements/1621768670.csv
tragic_semester_work_2/load_testing_measurements/1621779543.csv
tragic_semester_work_2/load_testing_measurements/1621783611.csv
tragic_semester_work_2/load_testing_measurements/UNIX TIMESTAMP.csv
tragic_semester_work_2/load_testing_plots/1621783586.jpg
tragic_semester_work_2/main.py
tragic_semester_work_2/quicksort.py
tragic_semester_work_2/Time.py
tragic_semester_work_2-0.1.6.dist-info/entry_points.txt
tragic_semester_work_2-0.1.6.dist-info/WHEEL
tragic_semester_work_2-0.1.6.dist-info/METADATA
tragic_semester_work_2-0.1.6.dist-info/RECORD
